stringtokenizer/__init__.py
stringtokenizer/stringtokenizer.py
stringtokenizer-1.1.9.dist-info/METADATA
stringtokenizer-1.1.9.dist-info/WHEEL
stringtokenizer-1.1.9.dist-info/top_level.txt
stringtokenizer-1.1.9.dist-info/RECORD
