Metadata-Version: 2.1
Name: stringtokenizer
Version: 1.1.9
Summary: A string tokenizer implementation
Home-page: UNKNOWN
Author: Tanmay Mandal
Author-email: tanmay.mandal@zohomail.in
License: MIT
Platform: UNKNOWN
Requires-Python: >=3.6
